odoo/addons/crm_lead_currency/README.rst
odoo/addons/crm_lead_currency/__init__.py
odoo/addons/crm_lead_currency/__manifest__.py
odoo/addons/crm_lead_currency/i18n/crm_lead_currency.pot
odoo/addons/crm_lead_currency/models/__init__.py
odoo/addons/crm_lead_currency/models/crm_lead.py
odoo/addons/crm_lead_currency/readme/CONFIGURE.rst
odoo/addons/crm_lead_currency/readme/CONTRIBUTORS.rst
odoo/addons/crm_lead_currency/readme/DESCRIPTION.rst
odoo/addons/crm_lead_currency/readme/INSTALL.rst
odoo/addons/crm_lead_currency/readme/USAGE.rst
odoo/addons/crm_lead_currency/static/description/icon.png
odoo/addons/crm_lead_currency/static/description/index.html
odoo/addons/crm_lead_currency/tests/__init__.py
odoo/addons/crm_lead_currency/tests/test_crm_opportunity_currency.py
odoo/addons/crm_lead_currency/views/crm_lead_opportunity_currency_views.xml
odoo12_addon_crm_lead_currency-12.0.1.0.1.dist-info/METADATA
odoo12_addon_crm_lead_currency-12.0.1.0.1.dist-info/WHEEL
odoo12_addon_crm_lead_currency-12.0.1.0.1.dist-info/top_level.txt
odoo12_addon_crm_lead_currency-12.0.1.0.1.dist-info/RECORD
